{"cameraMode":{"drawMode":0,"name":"Shaded","section":"Shading Mode"},"sceneLighting":true,"audioPlay":false,"sceneViewState":{"m_AlwaysRefresh":false,"showFog":true,"showSkybox":true,"showFlares":true,"showImageEffects":true,"showParticleSystems":true,"showVisualEffectGraphs":true,"m_FxEnabled":true},"in2DMode":false,"pivot":{"x":113.21473693847656,"y":-289.8680114746094,"z":61.847774505615237},"rotation":{"x":-0.4606229066848755,"y":-0.5355163216590881,"z":0.4545421302318573,"w":-0.5426415801048279},"size":225.30386352539063,"orthographic":false}